thl/__init__.py
thl/config.py
thl/errors.py
thl/model.py
thl/tokenizer.py
transformer_hierarchical_layers-0.2.0.dist-info/licenses/LICENSE
transformer_hierarchical_layers-0.2.0.dist-info/METADATA
transformer_hierarchical_layers-0.2.0.dist-info/WHEEL
transformer_hierarchical_layers-0.2.0.dist-info/top_level.txt
transformer_hierarchical_layers-0.2.0.dist-info/RECORD
