Metadata-Version: 2.4
Name: Transformer-Hierarchical-Layers
Version: 0.2.0
Summary: A non-Transformer hierarchical recurrent network with differentiable Gumbel-Softmax routing and bounded memory slots. Runs 7B+ parameter models layer-by-layer on low-budget GPUs.
Author-email: The EGen Team <mouhebzayani@erebustn.io>
License: MIT License
Project-URL: Homepage, https://github.com/EGen-V/Transformer-Hierarchical-Layers
Project-URL: Bug Tracker, https://github.com/EGen-V/Transformer-Hierarchical-Layers/issues
Project-URL: Logo, https://i.ibb.co/m5yN2JtW/Gemini-Generated-Image-kyoxiykyoxiykyodx.png
Project-URL: Documentation, https://github.com/EGen-V/Transformer-Hierarchical-Layers#readme
Keywords: deep-learning,llm,rnn,hierarchical,memory-augmented
Classifier: Development Status :: 3 - Alpha
Classifier: Intended Audience :: Science/Research
Classifier: License :: OSI Approved :: MIT License
Classifier: Programming Language :: Python :: 3
Classifier: Programming Language :: Python :: 3.8
Classifier: Programming Language :: Python :: 3.9
Classifier: Programming Language :: Python :: 3.10
Classifier: Programming Language :: Python :: 3.11
Classifier: Topic :: Scientific/Engineering :: Artificial Intelligence
Requires-Python: >=3.8
License-File: LICENSE
Requires-Dist: torch>=2.0.0
Requires-Dist: matplotlib>=3.0.0
Dynamic: license-file
